datasette_allow_permissions_debug/__init__.py
datasette_allow_permissions_debug-0.1.dist-info/METADATA
datasette_allow_permissions_debug-0.1.dist-info/WHEEL
datasette_allow_permissions_debug-0.1.dist-info/entry_points.txt
datasette_allow_permissions_debug-0.1.dist-info/top_level.txt
datasette_allow_permissions_debug-0.1.dist-info/RECORD
