Metadata-Version: 2.1
Name: datasette-allow-permissions-debug
Version: 0.1
Summary: Always allow access to /-/permissions, for debugging
Home-page: https://github.com/simonw/datasette-allow-permissions-debug
Author: Simon Willison
License: Apache License, Version 2.0
Project-URL: Issues, https://github.com/simonw/datasette-allow-permissions-debug/issues
Project-URL: CI, https://github.com/simonw/datasette-allow-permissions-debug/actions
Project-URL: Changelog, https://github.com/simonw/datasette-allow-permissions-debug/releases
Platform: UNKNOWN
Requires-Dist: datasette
Provides-Extra: test
Requires-Dist: pytest ; extra == 'test'
Requires-Dist: pytest-asyncio ; extra == 'test'
Requires-Dist: httpx ; extra == 'test'
